resim/py.typed
resim/sdk/__init__.py
resim/sdk/auth/__init__.py
resim/sdk/auth/check_expiration.py
resim/sdk/auth/const.py
resim/sdk/auth/device_code_client.py
resim/sdk/auth/username_password_client.py
resim/sdk/client/api/batches/__init__.py
resim/sdk/client/api/batches/cancel_batch.py
resim/sdk/client/api/batches/compare_batches.py
resim/sdk/client/api/batches/create_batch.py
resim/sdk/client/api/batches/create_batch_for_test_suite.py
resim/sdk/client/api/batches/create_batch_for_test_suite_revision.py
resim/sdk/client/api/batches/delete_batch_log.py
resim/sdk/client/api/batches/delete_job_log.py
resim/sdk/client/api/batches/get_batch.py
resim/sdk/client/api/batches/get_batch_log.py
resim/sdk/client/api/batches/get_batch_suggestions.py
resim/sdk/client/api/batches/get_event_for_job.py
resim/sdk/client/api/batches/get_job.py
resim/sdk/client/api/batches/get_job_log.py
resim/sdk/client/api/batches/list_all_jobs.py
resim/sdk/client/api/batches/list_batch_accounts.py
resim/sdk/client/api/batches/list_batch_errors.py
resim/sdk/client/api/batches/list_batch_logs_for_batch.py
resim/sdk/client/api/batches/list_batch_metrics.py
resim/sdk/client/api/batches/list_batch_metrics_data.py
resim/sdk/client/api/batches/list_batch_metrics_data_for_batch_metric_i_ds.py
resim/sdk/client/api/batches/list_batch_metrics_data_for_batch_metrics_data_i_ds.py
resim/sdk/client/api/batches/list_batch_metrics_for_batch_metric_i_ds.py
resim/sdk/client/api/batches/list_batches.py
resim/sdk/client/api/batches/list_batches_for_builds.py
resim/sdk/client/api/batches/list_batches_for_test_suite.py
resim/sdk/client/api/batches/list_batches_for_test_suite_revision.py
resim/sdk/client/api/batches/list_event_tags_for_job.py
resim/sdk/client/api/batches/list_events_for_job.py
resim/sdk/client/api/batches/list_job_logs_for_job.py
resim/sdk/client/api/batches/list_jobs.py
resim/sdk/client/api/batches/list_metrics_data_for_job.py
resim/sdk/client/api/batches/list_metrics_data_for_metric_i_ds.py
resim_sdk-1.0.1.dist-info/WHEEL
resim_sdk-1.0.1.dist-info/METADATA
resim_sdk-1.0.1.dist-info/RECORD
