Metadata-Version: 2.1
Name: resim_sdk
Author: ReSim Developers
Home-page: https://www.resim.ai/
License: Copyright 2025 ReSim, Inc.
Summary: ReSim SDK Libraries.
Classifier: License :: OSI Approved :: MIT License
Requires-Dist: attrs>=22.2.0
Requires-Dist: python-dateutil<3.0.0,>=2.8.1
Requires-Dist: httpx<0.29.0,>=0.20.0
Requires-Dist: numpy>=1.25.2
Requires-Dist: PyYAML>=6.0.0
Requires-Dist: httpx>=0.25.2
Version: 1.0.1
